vibe_security_ai/__init__.py
vibe_security_ai/cli.py
vibe_security_ai-1.0.2.dist-info/licenses/LICENSE
vibe_security_ai-1.0.2.dist-info/METADATA
vibe_security_ai-1.0.2.dist-info/WHEEL
vibe_security_ai-1.0.2.dist-info/entry_points.txt
vibe_security_ai-1.0.2.dist-info/top_level.txt
vibe_security_ai-1.0.2.dist-info/RECORD
