Metadata-Version: 2.4
Name: vibe-security-ai
Version: 1.0.2
Summary: 🔍 Vibe Security AI - A professional CLI tool for security analysis using Claude 4
Author-email: Cole McIntosh <colemcintosh6@gmail.com>
Maintainer-email: Cole McIntosh <colemcintosh6@gmail.com>
License-Expression: MIT
Project-URL: Homepage, https://github.com/colesmcintosh/vibe-check
Project-URL: Documentation, https://github.com/colesmcintosh/vibe-check#readme
Project-URL: Repository, https://github.com/colesmcintosh/vibe-check
Project-URL: Bug Reports, https://github.com/colesmcintosh/vibe-check/issues
Keywords: security,analysis,cli,claude,ai,vulnerability,scanner,code-analysis,static-analysis,devops,security-tools
Classifier: Development Status :: 4 - Beta
Classifier: Intended Audience :: Developers
Classifier: Intended Audience :: System Administrators
Classifier: Topic :: Security
Classifier: Topic :: Software Development :: Quality Assurance
Classifier: Topic :: Software Development :: Testing
Classifier: Operating System :: OS Independent
Classifier: Programming Language :: Python :: 3
Classifier: Programming Language :: Python :: 3.8
Classifier: Programming Language :: Python :: 3.9
Classifier: Programming Language :: Python :: 3.10
Classifier: Programming Language :: Python :: 3.11
Classifier: Programming Language :: Python :: 3.12
Classifier: Environment :: Console
Classifier: Natural Language :: English
Requires-Python: >=3.8
License-File: LICENSE
Requires-Dist: click<9.0.0,>=8.1.0
Requires-Dist: anthropic<1.0.0,>=0.34.0
Requires-Dist: rich<14.0.0,>=13.0.0
Dynamic: license-file
